nester.py
nester_package-1.3.1.dist-info/LICENSE.txt
nester_package-1.3.1.dist-info/METADATA
nester_package-1.3.1.dist-info/WHEEL
nester_package-1.3.1.dist-info/top_level.txt
nester_package-1.3.1.dist-info/RECORD
