Metadata-Version: 2.1
Name: nester-package
Version: 1.3.1
Summary: Printing each items in list (nested or not) on new line with or without required tab spaces/indent
Home-page: 
Author: SonaM
Author-email: sonalimetkar1@gmail.com
License-File: LICENSE.txt
